{
   "took":0,
   "timed_out":false,
   "_shards":{
      "total":5,
      "successful":5,
      "skipped":0,
      "failed":0
   },
   "hits":{
      "total":1,
      "max_score":0,
      "hits":[
         {
            "_index":"bank",
            "_type":"account",
            "_id":"855",
            "_score":0,
            "_source":{
               "account_number":855,
               "balance":40170,
               "firstname":"Mia",
               "lastname":"Stevens",
               "age":31,
               "gender":"F",
               "address":"326 Driggs Avenue",
               "employer":"Aeora",
               "email":"miastevens@aeora.com",
               "city":"Delwood",
               "state":"IL"
            }
         }
      ]
   }
}